{
    "target": "cpu",
    "0": {
        "0": {
            "0": {
                "from": 14,
                "to": 18
            },
            "6": {
                "from": 19,
                "to": 19
            },
            "5": {
                "from": 20,
                "to": 31
            },
            "2": {
                "from": 21,
                "to": 21
            },
            "3": {
                "from": 22,
                "to": 22
            },
            "7": {
                "from": 32,
                "to": 42
            },
            "1": {
                "from": 43,
                "to": 46
            }
        }
    }
}